Workbook

Sheet 5. Summary
A1: 🏠 HOME PURCHASE DECISION SUMMARY
A3: KEY METRICS (After 10 Years)
B4: BUY Scenario | C4: RENT Scenario | D4: Difference
A5: Property Value | B5: ='4. Buy vs Rent'!B14 | C5: =0 | D5: =B5-C5
A6: Loan Balance | B6: ='4. Buy vs Rent'!C14 | C6: =0 | D6: =B6-C6
A7: Net Equity | B7: ='4. Buy vs Rent'!D14 | C7: =0 | D7: =B7-C7
A8: SIP Portfolio | B8: ='4. Buy vs Rent'!G14-'4. Buy vs Rent'!D14 | C8: ='4. Buy vs Rent'!H14 | D8: =B8-C8
A9: TOTAL NET WORTH | B9: ='4. Buy vs Rent'!G14 | C9: ='4. Buy vs Rent'!H14 | D9: =B9-C9
A11: =IF(C9>B9,"🏆 RENT WINS by ₹"&TEXT(ABS(D9),"#,##0"),"🏆 BUY WINS by ₹"&TEXT(ABS(D9),"#,##0"))
A13: 💡 TO USE: Go to '1. Inputs' sheet → Change yellow cells → All sheets update!
A15: Current Inputs
A16: Property Price | B16: ='1. Inputs'!B4 | C16: EMI | D16: ='2. Amortization'!C4
A17: Loan Amount | B17: ='1. Inputs'!B4-'1. Inputs'!B5-'1. Inputs'!B6 | C17: EMI % of Income | D17: ='2. Amortization'!C4/('1. Inputs'!B14+'1. Inputs'!B15)
A18: Interest Rate | B18: ='1. Inputs'!B9 | C18: Property Value (10Y) | D18: ='4. Buy vs Rent'!B14

Sheet 1. Inputs
A1: HOME PURCHASE CALCULATOR - CHANGE YELLOW CELLS
A3: Property Details
A4: Property Price | B4: 14500000
A5: Stamp & Registration | B5: 1000000
A6: Down Payment | B6: 4000000
A8: Loan Terms
A9: Interest Rate (Annual) | B9: 0.0715
A10: Loan Tenure (Years) | B10: 15
A11: Analysis Period (Years) | B11: 10
A13: Income (Monthly)
A14: Husband Salary | B14: 225000
A15: Wife Salary | B15: 150000
A17: Market Assumptions
A18: Current Monthly Rent | B18: 27000
A19: Rent Growth Rate | B19: 0.05
A20: Property Appreciation Rate | B20: 0.04
A21: SIP Return Rate | B21: 0.12
A22: Additional Monthly SIP (if buying) | B22: 30000

Sheet 2. Amortization
A1: MONTH-BY-MONTH LOAN REPAYMENT
A3: Month | B3: Opening Balance | C3: EMI | D3: Interest | E3: Principal | F3: Closing Balance
A4: 1 | B4: ='1. Inputs'!B4-'1. Inputs'!B5-'1. Inputs'!B6 | C4: =-PMT('1. Inputs'!B9/12,'1. Inputs'!B10*12,B4) | D4: =B4*'1. Inputs'!B9/12 | E4: =C4-D4 | F4: =MAX(0,B4-E4)
A5: =A4+1 | B5: =F4 | C5: =$C$4 | D5: =B5*'1. Inputs'!$B$9/12 | E5: =C5-D5 | F5: =MAX(0,B5-E5)
A6: =A5+1 | B6: =F5 | C6: =$C$4 | D6: =B6*'1. Inputs'!$B$9/12 | E6: =C6-D6 | F6: =MAX(0,B6-E6)
A7: =A6+1 | B7: =F6 | C7: =$C$4 | D7: =B7*'1. Inputs'!$B$9/12 | E7: =C7-D7 | F7: =MAX(0,B7-E7)
A8: =A7+1 | B8: =F7 | C8: =$C$4 | D8: =B8*'1. Inputs'!$B$9/12 | E8: =C8-D8 | F8: =MAX(0,B8-E8)
A9: =A8+1 | B9: =F8 | C9: =$C$4 | D9: =B9*'1. Inputs'!$B$9/12 | E9: =C9-D9 | F9: =MAX(0,B9-E9)
A10: =A9+1 | B10: =F9 | C10: =$C$4 | D10: =B10*'1. Inputs'!$B$9/12 | E10: =C10-D10 | F10: =MAX(0,B10-E10)
A11: =A10+1 | B11: =F10 | C11: =$C$4 | D11: =B11*'1. Inputs'!$B$9/12 | E11: =C11-D11 | F11: =MAX(0,B11-E11)
A12: =A11+1 | B12: =F11 | C12: =$C$4 | D12: =B12*'1. Inputs'!$B$9/12 | E12: =C12-D12 | F12: =MAX(0,B12-E12)
A13: =A12+1 | B13: =F12 | C13: =$C$4 | D13: =B13*'1. Inputs'!$B$9/12 | E13: =C13-D13 | F13: =MAX(0,B13-E13)
A14: =A13+1 | B14: =F13 | C14: =$C$4 | D14: =B14*'1. Inputs'!$B$9/12 | E14: =C14-D14 | F14: =MAX(0,B14-E14)
A15: =A14+1 | B15: =F14 | C15: =$C$4 | D15: =B15*'1. Inputs'!$B$9/12 | E15: =C15-D15 | F15: =MAX(0,B15-E15)
A16: =A15+1 | B16: =F15 | C16: =$C$4 | D16: =B16*'1. Inputs'!$B$9/12 | E16: =C16-D16 | F16: =MAX(0,B16-E16)
... A183: =A182+1 | B183: =F182 | C183: =$C$4 | D183: =B183*'1. Inputs'!$B$9/12 | E183: =C183-D183 | F183: =MAX(0,B183-E183)

Sheet 3. Yearly Summary
A1: YEAR-BY-YEAR LOAN SUMMARY
A3: Year | B3: Opening Balance | C3: Principal Paid | D3: Interest Paid | E3: Closing Balance
A4: 1 | B4: ='2. Amortization'!B4 | C4: =SUM('2. Amortization'!E4:E15) | D4: =SUM('2. Amortization'!D4:D15) | E4: ='2. Amortization'!F15
A5: 2 | B5: ='2. Amortization'!B16 | C5: =SUM('2. Amortization'!E16:E27) | D5: =SUM('2. Amortization'!D16:D27) | E5: ='2. Amortization'!F27
A6: 3 | B6: ='2. Amortization'!B28 | C6: =SUM('2. Amortization'!E28:E39) | D6: =SUM('2. Amortization'!D28:D39) | E6: ='2. Amortization'!F39
A7: 4 | B7: ='2. Amortization'!B40 | C7: =SUM('2. Amortization'!E40:E51) | D7: =SUM('2. Amortization'!D40:D51) | E7: ='2. Amortization'!F51
A8: 5 | B8: ='2. Amortization'!B52 | C8: =SUM('2. Amortization'!E52:E63) | D8: =SUM('2. Amortization'!D52:D63) | E8: ='2. Amortization'!F63
A9: 6 | B9: ='2. Amortization'!B64 | C9: =SUM('2. Amortization'!E64:E75) | D9: =SUM('2. Amortization'!D64:D75) | E9: ='2. Amortization'!F75
A10: 7 | B10: ='2. Amortization'!B76 | C10: =SUM('2. Amortization'!E76:E87) | D10: =SUM('2. Amortization'!D76:D87) | E10: ='2. Amortization'!F87
A11: 8 | B11: ='2. Amortization'!B88 | C11: =SUM('2. Amortization'!E88:E99) | D11: =SUM('2. Amortization'!D88:D99) | E11: ='2. Amortization'!F99
A12: 9 | B12: ='2. Amortization'!B100 | C12: =SUM('2. Amortization'!E100:E111) | D12: =SUM('2. Amortization'!D100:D111) | E12: ='2. Amortization'!F111
A13: 10 | B13: ='2. Amortization'!B112 | C13: =SUM('2. Amortization'!E112:E123) | D13: =SUM('2. Amortization'!D112:D123) | E13: ='2. Amortization'!F123
A14: 11 | B14: ='2. Amortization'!B124 | C14: =SUM('2. Amortization'!E124:E135) | D14: =SUM('2. Amortization'!D124:D135) | E14: ='2. Amortization'!F135
A15: 12 | B15: ='2. Amortization'!B136 | C15: =SUM('2. Amortization'!E136:E147) | D15: =SUM('2. Amortization'!D136:D147) | E15: ='2. Amortization'!F147
A16: 13 | B16: ='2. Amortization'!B148 | C16: =SUM('2. Amortization'!E148:E159) | D16: =SUM('2. Amortization'!D148:D159) | E16: ='2. Amortization'!F159
A17: 14 | B17: ='2. Amortization'!B160 | C17: =SUM('2. Amortization'!E160:E171) | D17: =SUM('2. Amortization'!D160:D171) | E17: ='2. Amortization'!F171
A18: 15 | B18: ='2. Amortization'!B172 | C18: =SUM('2. Amortization'!E172:E183) | D18: =SUM('2. Amortization'!D172:D183) | E18: ='2. Amortization'!F183

Sheet 4. Buy vs Rent
A1: BUY vs RENT NET WORTH COMPARISON
A3: Year | B3: Property Value | C3: Loan Balance | D3: Net Equity | E3: Rent Paid | F3: SIP Value | G3: Net Worth (Buy) | H3: Net Worth (Rent)
A4: 0 | B4: ='1. Inputs'!B4 | C4: ='2. Amortization'!B4 | D4: =-'1. Inputs'!B6 | E4: 0 | F4: ='1. Inputs'!B6 | G4: =B4-C4-'1. Inputs'!B6 | H4: =F4
A5: 1 | B5: ='1. Inputs'!$B$4*(1+'1. Inputs'!$B$20)^A5 | C5: ='3. Yearly Summary'!E4 | D5: =B5-C5 | E5: ='1. Inputs'!$B$18*12*(1+'1. Inputs'!$B$19)^(A5-1) | F5: =F4*(1+'1. Inputs'!$B$21)+('2. Amortization'!$C$4*12)*(((1+'1. Inputs'!$B$21)-1)/'1. Inputs'!$B$21)*(1+'1. Inputs'!$B$21) | G5: =D5+('1. Inputs'!B22*12*A5)*(((1+'1. Inputs'!$B$21)^A5-1)/'1. Inputs'!$B$21)*(1+'1. Inputs'!$B$21) | H5: =F5
A6: 2 | B6: ='1. Inputs'!$B$4*(1+'1. Inputs'!$B$20)^A6 | C6: ='3. Yearly Summary'!E5 | D6: =B6-C6 | E6: ='1. Inputs'!$B$18*12*(1+'1. Inputs'!$B$19)^(A6-1) | F6: =F5*(1+'1. Inputs'!$B$21)+('2. Amortization'!$C$4*12)*(((1+'1. Inputs'!$B$21)-1)/'1. Inputs'!$B$21)*(1+'1. Inputs'!$B$21) | G6: =D6+('1. Inputs'!B22*12*A6)*(((1+'1. Inputs'!$B$21)^A6-1)/'1. Inputs'!$B$21)*(1+'1. Inputs'!$B$21) | H6: =F6
A7: 3 | B7: ='1. Inputs'!$B$4*(1+'1. Inputs'!$B$20)^A7 | C7: ='3. Yearly Summary'!E6 | D7: =B7-C7 | E7: ='1. Inputs'!$B$18*12*(1+'1. Inputs'!$B$19)^(A7-1) | F7: =F6*(1+'1. Inputs'!$B$21)+('2. Amortization'!$C$4*12)*(((1+'1. Inputs'!$B$21)-1)/'1. Inputs'!$B$21)*(1+'1. Inputs'!$B$21) | G7: =D7+('1. Inputs'!B22*12*A7)*(((1+'1. Inputs'!$B$21)^A7-1)/'1. Inputs'!$B$21)*(1+'1. Inputs'!$B$21) | H7: =F7
A8: 4 | B8: ='1. Inputs'!$B$4*(1+'1. Inputs'!$B$20)^A8 | C8: ='3. Yearly Summary'!E7 | D8: =B8-C8 | E8: ='1. Inputs'!$B$18*12*(1+'1. Inputs'!$B$19)^(A8-1) | F8: =F7*(1+'1. Inputs'!$B$21)+('2. Amortization'!$C$4*12)*(((1+'1. Inputs'!$B$21)-1)/'1. Inputs'!$B$21)*(1+'1. Inputs'!$B$21) | G8: =D8+('1. Inputs'!B22*12*A8)*(((1+'1. Inputs'!$B$21)^A8-1)/'1. Inputs'!$B$21)*(1+'1. Inputs'!$B$21) | H8: =F8
A9: 5 | B9: ='1. Inputs'!$B$4*(1+'1. Inputs'!$B$20)^A9 | C9: ='3. Yearly Summary'!E8 | D9: =B9-C9 | E9: ='1. Inputs'!$B$18*12*(1+'1. Inputs'!$B$19)^(A9-1) | F9: =F8*(1+'1. Inputs'!$B$21)+('2. Amortization'!$C$4*12)*(((1+'1. Inputs'!$B$21)-1)/'1. Inputs'!$B$21)*(1+'1. Inputs'!$B$21) | G9: =D9+('1. Inputs'!B22*12*A9)*(((1+'1. Inputs'!$B$21)^A9-1)/'1. Inputs'!$B$21)*(1+'1. Inputs'!$B$21) | H9: =F9
A10: 6 | B10: ='1. Inputs'!$B$4*(1+'1. Inputs'!$B$20)^A10 | C10: ='3. Yearly Summary'!E9 | D10: =B10-C10 | E10: ='1. Inputs'!$B$18*12*(1+'1. Inputs'!$B$19)^(A10-1) | F10: =F9*(1+'1. Inputs'!$B$21)+('2. Amortization'!$C$4*12)*(((1+'1. Inputs'!$B$21)-1)/'1. Inputs'!$B$21)*(1+'1. Inputs'!$B$21) | G10: =D10+('1. Inputs'!B22*12*A10)*(((1+'1. Inputs'!$B$21)^A10-1)/'1. Inputs'!$B$21)*(1+'1. Inputs'!$B$21) | H10: =F10
A11: 7 | B11: ='1. Inputs'!$B$4*(1+'1. Inputs'!$B$20)^A11 | C11: ='3. Yearly Summary'!E10 | D11: =B11-C11 | E11: ='1. Inputs'!$B$18*12*(1+'1. Inputs'!$B$19)^(A11-1) | F11: =F10*(1+'1. Inputs'!$B$21)+('2. Amortization'!$C$4*12)*(((1+'1. Inputs'!$B$21)-1)/'1. Inputs'!$B$21)*(1+'1. Inputs'!$B$21) | G11: =D11+('1. Inputs'!B22*12*A11)*(((1+'1. Inputs'!$B$21)^A11-1)/'1. Inputs'!$B$21)*(1+'1. Inputs'!$B$21) | H11: =F11
A12: 8 | B12: ='1. Inputs'!$B$4*(1+'1. Inputs'!$B$20)^A12 | C12: ='3. Yearly Summary'!E11 | D12: =B12-C12 | E12: ='1. Inputs'!$B$18*12*(1+'1. Inputs'!$B$19)^(A12-1) | F12: =F11*(1+'1. Inputs'!$B$21)+('2. Amortization'!$C$4*12)*(((1+'1. Inputs'!$B$21)-1)/'1. Inputs'!$B$21)*(1+'1. Inputs'!$B$21) | G12: =D12+('1. Inputs'!B22*12*A12)*(((1+'1. Inputs'!$B$21)^A12-1)/'1. Inputs'!$B$21)*(1+'1. Inputs'!$B$21) | H12: =F12
A13: 9 | B13: ='1. Inputs'!$B$4*(1+'1. Inputs'!$B$20)^A13 | C13: ='3. Yearly Summary'!E12 | D13: =B13-C13 | E13: ='1. Inputs'!$B$18*12*(1+'1. Inputs'!$B$19)^(A13-1) | F13: =F12*(1+'1. Inputs'!$B$21)+('2. Amortization'!$C$4*12)*(((1+'1. Inputs'!$B$21)-1)/'1. Inputs'!$B$21)*(1+'1. Inputs'!$B$21) | G13: =D13+('1. Inputs'!B22*12*A13)*(((1+'1. Inputs'!$B$21)^A13-1)/'1. Inputs'!$B$21)*(1+'1. Inputs'!$B$21) | H13: =F13
A14: 10 | B14: ='1. Inputs'!$B$4*(1+'1. Inputs'!$B$20)^A14 | C14: ='3. Yearly Summary'!E13 | D14: =B14-C14 | E14: ='1. Inputs'!$B$18*12*(1+'1. Inputs'!$B$19)^(A14-1) | F14: =F13*(1+'1. Inputs'!$B$21)+('2. Amortization'!$C$4*12)*(((1+'1. Inputs'!$B$21)-1)/'1. Inputs'!$B$21)*(1+'1. Inputs'!$B$21) | G14: =D14+('1. Inputs'!B22*12*A14)*(((1+'1. Inputs'!$B$21)^A14-1)/'1. Inputs'!$B$21)*(1+'1. Inputs'!$B$21) | H14: =F14
